odoo/addons/delivery_local_pickup/README.rst
odoo/addons/delivery_local_pickup/__init__.py
odoo/addons/delivery_local_pickup/__manifest__.py
odoo/addons/delivery_local_pickup/controllers/__init__.py
odoo/addons/delivery_local_pickup/controllers/main.py
odoo/addons/delivery_local_pickup/i18n/delivery_local_pickup.pot
odoo/addons/delivery_local_pickup/models/__init__.py
odoo/addons/delivery_local_pickup/models/delivery_carrier.py
odoo/addons/delivery_local_pickup/readme/CONFIGURE.rst
odoo/addons/delivery_local_pickup/readme/CONTRIBUTORS.rst
odoo/addons/delivery_local_pickup/readme/DESCRIPTION.rst
odoo/addons/delivery_local_pickup/readme/USAGE.rst
odoo/addons/delivery_local_pickup/static/description/icon.png
odoo/addons/delivery_local_pickup/static/description/index.html
odoo/addons/delivery_local_pickup/static/src/js/local_pickup_tour.js
odoo/addons/delivery_local_pickup/tests/__init__.py
odoo/addons/delivery_local_pickup/tests/common.py
odoo/addons/delivery_local_pickup/tests/test_delivery_local_pickup.py
odoo/addons/delivery_local_pickup/tests/test_website.py
odoo/addons/delivery_local_pickup/views/assets.xml
odoo/addons/delivery_local_pickup/views/delivery_carrier_view.xml
odoo/addons/delivery_local_pickup/views/website_templates.xml
odoo13_addon_delivery_local_pickup-13.0.1.0.1.dev3.dist-info/METADATA
odoo13_addon_delivery_local_pickup-13.0.1.0.1.dev3.dist-info/WHEEL
odoo13_addon_delivery_local_pickup-13.0.1.0.1.dev3.dist-info/top_level.txt
odoo13_addon_delivery_local_pickup-13.0.1.0.1.dev3.dist-info/RECORD
